beyondml/__init__.py
beyondml/pt/__init__.py
beyondml/pt/layers/Conv2D.py
beyondml/pt/layers/Conv3D.py
beyondml/pt/layers/Dense.py
beyondml/pt/layers/FilterLayer.py
beyondml/pt/layers/MaskedConv2D.py
beyondml/pt/layers/MaskedConv3D.py
beyondml/pt/layers/MaskedDense.py
beyondml/pt/layers/MaskedMultiHeadAttention.py
beyondml/pt/layers/MaskedTransformerDecoderLayer.py
beyondml/pt/layers/MaskedTransformerEncoderLayer.py
beyondml/pt/layers/MultiConv2D.py
beyondml/pt/layers/MultiConv3D.py
beyondml/pt/layers/MultiDense.py
beyondml/pt/layers/MultiMaskedConv2D.py
beyondml/pt/layers/MultiMaskedConv3D.py
beyondml/pt/layers/MultiMaskedDense.py
beyondml/pt/layers/MultiMaxPool2D.py
beyondml/pt/layers/MultiMaxPool3D.py
beyondml/pt/layers/MultitaskNormalization.py
beyondml/pt/layers/SelectorLayer.py
beyondml/pt/layers/SparseConv2D.py
beyondml/pt/layers/SparseConv3D.py
beyondml/pt/layers/SparseDense.py
beyondml/pt/layers/SparseMultiConv2D.py
beyondml/pt/layers/SparseMultiConv3D.py
beyondml/pt/layers/SparseMultiDense.py
beyondml/pt/layers/__init__.py
beyondml/pt/utils/__init__.py
beyondml/pt/utils/utils.py
beyondml/tflow/__init__.py
beyondml/tflow/layers/FilterLayer.py
beyondml/tflow/layers/MaskedConv2D.py
beyondml/tflow/layers/MaskedConv3D.py
beyondml/tflow/layers/MaskedDense.py
beyondml/tflow/layers/MultiConv2D.py
beyondml/tflow/layers/MultiConv3D.py
beyondml/tflow/layers/MultiDense.py
beyondml/tflow/layers/MultiMaskedConv2D.py
beyondml/tflow/layers/MultiMaskedConv3D.py
beyondml/tflow/layers/MultiMaskedDense.py
beyondml/tflow/layers/MultiMaxPool2D.py
beyondml/tflow/layers/MultiMaxPool3D.py
beyondml/tflow/layers/MultitaskNormalization.py
beyondml/tflow/layers/SelectorLayer.py
beyondml/tflow/layers/SparseConv2D.py
beyondml/tflow/layers/SparseConv3D.py
beyondml/tflow/layers/SparseDense.py
beyondml/tflow/layers/SparseMultiConv2D.py
beyondml/tflow/layers/SparseMultiConv3D.py
beyondml/tflow/layers/SparseMultiDense.py
beyondml/tflow/layers/SumLayer.py
beyondml/tflow/layers/__init__.py
beyondml-0.1.7.dist-info/LICENSE
beyondml-0.1.7.dist-info/METADATA
beyondml-0.1.7.dist-info/WHEEL
beyondml-0.1.7.dist-info/top_level.txt
beyondml-0.1.7.dist-info/RECORD
