Metadata-Version: 2.1
Name: beyondml
Version: 0.1.7
Summary: Package containing utilities for implementing RSN2/MANN
Home-page: https://github.com/Beyond-ML-Labs/BeyondML
Author: The AI Squared Team
Author-email: mann@squared.ai
License: Apache 2.0
License-File: LICENSE
Requires-Dist: tensorflow <=2.13
Requires-Dist: torch
